README.rst
setup.py
scheduler/__init__.py
scheduler_cron.egg-info/PKG-INFO
scheduler_cron.egg-info/SOURCES.txt
scheduler_cron.egg-info/dependency_links.txt
scheduler_cron.egg-info/requires.txt
scheduler_cron.egg-info/top_level.txt