Metadata-Version: 1.0
Name: scheduler-cron
Version: 0.1
Summary: Python task scheduling with cron expression
Home-page: https://github.com/mehrdadmhd/scheduler-py
Author: Mehrdad Mahmoudi
Author-email: mehrdad@asiatech.ir
License: UNKNOWN
Keywords: pip,schedule,schedule,python,python3,job,cron
Platform: UNKNOWN
